[
  {
    "title": "JYSK",
    "description": "JYSK надає знижку на всі меблі та аксесуари",
    "discount_value": "8",
    "location": "Kyiv",
    "category": "shop",
    "start_date": 1673424000000,
    "end_date": 1673424000000,
    "img": "images/jysk.jpg"
  },
  {
    "title": "SomeCafe",
    "description": "SomeCafe надає знижку на всі бізнес-ланчі",
    "discount_value": "20",
    "location": "Kyiv",
    "category": "cafe",
    "start_date": 1673424000000,
    "end_date": 1673424000000,
    "img": "images/somecafe.jpg"
  },
  {
    "title": "Veterano Pizza",
    "description": "Veterano Pizza залучає ветеранів до роботи",
    "discount_value": "15",
    "location": "Lviv",
    "category": "restaurant",
    "start_date": 1673424000000,
    "end_date": 1673424000000,
    "img": "images/veteranopizza.jpg"
  }
]
